mnnllzz/__init__.py
mnnllzz/__main__.py
mnnllzz/mnnllzz.py
mnnllzz-1.3.4.dist-info/LICENSE.txt
mnnllzz-1.3.4.dist-info/METADATA
mnnllzz-1.3.4.dist-info/WHEEL
mnnllzz-1.3.4.dist-info/top_level.txt
mnnllzz-1.3.4.dist-info/RECORD
