Metadata-Version: 2.1
Name: mnnllzz
Version: 1.3.4
Summary: Create randomized tests
Home-page: https://github.com/atomadin/mnnllzz
Download-URL: https://github.com/atomadin/mnnllzz/archive/refs/tags/v_1.3.4.tar.gz
Author: Andrea Tomadin
Author-email: andrea.tomadin@unipi.it
License: MIT
Keywords: TEST,EXAM
Classifier: Development Status :: 5 - Production/Stable
Classifier: License :: OSI Approved :: MIT License
Classifier: Programming Language :: Python :: 3
License-File: LICENSE.txt
Requires-Dist: numpy
